hjson/__init__.py
hjson/compat.py
hjson/decoder.py
hjson/encoder.py
hjson/encoderH.py
hjson/ordered_dict.py
hjson/scanner.py
hjson/tool.py
hjson/tests/__init__.py
hjson/tests/test_bigint_as_string.py
hjson/tests/test_bitsize_int_as_string.py
hjson/tests/test_check_circular.py
hjson/tests/test_decimal.py
hjson/tests/test_decode.py
hjson/tests/test_default.py
hjson/tests/test_dump.py
hjson/tests/test_encode_basestring_ascii.py
hjson/tests/test_errors.py
hjson/tests/test_fail.py
hjson/tests/test_float.py
hjson/tests/test_for_json.py
hjson/tests/test_hjson.py
hjson/tests/test_indent.py
hjson/tests/test_item_sort_key.py
hjson/tests/test_namedtuple.py
hjson/tests/test_pass1.py
hjson/tests/test_pass2.py
hjson/tests/test_pass3.py
hjson/tests/test_recursion.py
hjson/tests/test_scanstring.py
hjson/tests/test_separators.py
hjson/tests/test_tool.py
hjson/tests/test_tuple.py
hjson/tests/test_unicode.py
hjson-3.0.1.data/scripts/hjson
hjson-3.0.1.data/scripts/hjson.cmd
hjson-3.0.1.dist-info/LICENSE.txt
hjson-3.0.1.dist-info/METADATA
hjson-3.0.1.dist-info/WHEEL
hjson-3.0.1.dist-info/top_level.txt
hjson-3.0.1.dist-info/RECORD
