Metadata-Version: 1.1
Name: hjson
Version: 3.0.1
Summary: Hjson, a user interface for JSON.
Home-page: http://github.com/hjson/hjson-py
Author: Christian Zangl
Author-email: laktak@cdak.net
License: MIT License
Keywords: json comments configuration
Platform: any
